nlm_utils/__init__.py
nlm_utils/cache/__init__.py
nlm_utils/cache/base_agent.py
nlm_utils/cache/cache.py
nlm_utils/cache/file_agent.py
nlm_utils/cache/memory_agent.py
nlm_utils/cache/mongodb_agent.py
nlm_utils/cache/redis_agent.py
nlm_utils/grpc_client/__init__.py
nlm_utils/grpc_client/search_engine_client.py
nlm_utils/grpc_pb2/__init__.py
nlm_utils/grpc_pb2/search_engine_pb2.py
nlm_utils/grpc_pb2/search_engine_pb2_grpc.py
nlm_utils/model_client/__init__.py
nlm_utils/model_client/bart_client.py
nlm_utils/model_client/classification.py
nlm_utils/model_client/connection_pool.py
nlm_utils/model_client/constants.py
nlm_utils/model_client/encoder.py
nlm_utils/model_client/flan_t5_client.py
nlm_utils/model_client/nlp_client.py
nlm_utils/model_client/openai_client.py
nlm_utils/model_client/yolo_client.py
nlm_utils/parsers/__init__.py
nlm_utils/parsers/constants.py
nlm_utils/parsers/location_parser.py
nlm_utils/parsers/value_parser.py
nlm_utils/rabbitmq/__init__.py
nlm_utils/rabbitmq/producer.py
nlm_utils/storage/__init__.py
nlm_utils/storage/local/__init__.py
nlm_utils/storage/local/local_filestorage.py
nlm_utils/storage/minio/__init__.py
nlm_utils/storage/minio/minio_filestorage.py
nlm_utils/utils/__init__.py
nlm_utils/utils/answer_type.py
nlm_utils/utils/bm25.py
nlm_utils/utils/evaluation_utils.py
nlm_utils/utils/file_utils.py
nlm_utils/utils/http_client.py
nlm_utils/utils/package_version.py
nlm_utils/utils/preprocessing.py
nlm_utils/utils/query_preprocessing.py
nlm_utils/utils/utils.py
tests/__init__.py
tests/cache/__init__.py
tests/cache/test_file_cache.py
tests/cache/test_memory_cache.py
tests/cache/test_mongodb_cache.py
tests/cache/test_redis_cache.py
tests/model_client/__init__.py
tests/model_client/test_classification.py
tests/model_client/test_encoder.py
tests/parsers/__init__.py
tests/parsers/test_count_parser.py
tests/parsers/test_date_parser.py
tests/parsers/test_distance_parser.py
tests/parsers/test_location_parser.py
tests/parsers/test_money_parser.py
nlm_utils-0.1.2.dist-info/LICENSE.txt
nlm_utils-0.1.2.dist-info/METADATA
nlm_utils-0.1.2.dist-info/NOTICE.txt
nlm_utils-0.1.2.dist-info/WHEEL
nlm_utils-0.1.2.dist-info/top_level.txt
nlm_utils-0.1.2.dist-info/RECORD
