Metadata-Version: 2.1
Name: nlm-utils
Version: 0.1.2
Summary: Common utilities used by all nlm-* libraries.
Home-page: https://github.com/nlmatics/nlm-utils
Author: Ambika Sukla
Author-email: ambika.sukla@nlmatics.com
License: Apache License 2.0
Classifier: Development Status :: 5 - Production/Stable
Classifier: Development Status :: 1 - Planning
Classifier: Intended Audience :: Science/Research
Classifier: Intended Audience :: Developers
Classifier: Intended Audience :: Legal Industry
Classifier: License :: OSI Approved :: Apache Software License
Classifier: Operating System :: POSIX :: Linux
Classifier: Programming Language :: Python :: 3 :: Only
License-File: LICENSE.txt
License-File: NOTICE.txt
Requires-Dist: aiohttp ==3.8.5
Requires-Dist: dateparser
Requires-Dist: dnspython ==2.1.0
Requires-Dist: word2number
Requires-Dist: minio ==7.1.0
Requires-Dist: money ==1.3.0
Requires-Dist: msgpack ==1.0.2
Requires-Dist: nltk ==3.6.2
Requires-Dist: numpy ==1.24.4
Requires-Dist: openai
Requires-Dist: pymongo ==3.11.4
Requires-Dist: redis ==3.5.3
Requires-Dist: tiktoken
Requires-Dist: urllib3 ==1.26.6
Requires-Dist: xxhash ==2.0.2
Requires-Dist: python-magic ==0.4.22
Requires-Dist: dicttoxml
